dynamic_path_manager/__init__.py
dynamic_path_manager/manager.py
dynamic_path_manager-1.0.1.dist-info/licenses/LICENSE
dynamic_path_manager-1.0.1.dist-info/METADATA
dynamic_path_manager-1.0.1.dist-info/WHEEL
dynamic_path_manager-1.0.1.dist-info/entry_points.txt
dynamic_path_manager-1.0.1.dist-info/top_level.txt
dynamic_path_manager-1.0.1.dist-info/RECORD
