Metadata-Version: 2.4
Name: dynamic-path-manager
Version: 1.0.1
Summary: A Python context manager for temporarily adding and removing paths from sys.path
Author-email: Your Name <your.email@example.com>
Maintainer-email: Your Name <your.email@example.com>
License: MIT License
Project-URL: Homepage, https://github.com/yourusername/dynamic-path-manager
Project-URL: Documentation, https://dynamic-path-manager.readthedocs.io/
Project-URL: Repository, https://github.com/yourusername/dynamic-path-manager.git
Project-URL: Bug Tracker, https://github.com/yourusername/dynamic-path-manager/issues
Keywords: python,import,sys.path,context-manager,dynamic-import
Classifier: Development Status :: 5 - Production/Stable
Classifier: Intended Audience :: Developers
Classifier: License :: OSI Approved :: MIT License
Classifier: Operating System :: OS Independent
Classifier: Programming Language :: Python :: 3
Classifier: Programming Language :: Python :: 3.7
Classifier: Programming Language :: Python :: 3.8
Classifier: Programming Language :: Python :: 3.9
Classifier: Programming Language :: Python :: 3.10
Classifier: Programming Language :: Python :: 3.11
Classifier: Programming Language :: Python :: 3.12
Classifier: Topic :: Software Development :: Libraries :: Python Modules
Classifier: Topic :: System :: Filesystems
Requires-Python: >=3.7
License-File: LICENSE
Provides-Extra: dev
Requires-Dist: pytest>=6.0; extra == "dev"
Requires-Dist: pytest-cov>=2.0; extra == "dev"
Requires-Dist: black>=21.0; extra == "dev"
Requires-Dist: flake8>=3.8; extra == "dev"
Requires-Dist: mypy>=0.800; extra == "dev"
Requires-Dist: isort>=5.0; extra == "dev"
Provides-Extra: docs
Requires-Dist: sphinx>=4.0; extra == "docs"
Requires-Dist: sphinx-rtd-theme>=1.0; extra == "docs"
Dynamic: license-file
